browser_memory_monitor/__init__.py
browser_memory_monitor/args.py
browser_memory_monitor/core.py
browser_memory_monitor/ctrl_c.py
browser_memory_monitor/main.py
browser_memory_monitor/py.typed
browser_memory_monitor-0.0.3.dist-info/LICENSE.md
browser_memory_monitor-0.0.3.dist-info/METADATA
browser_memory_monitor-0.0.3.dist-info/WHEEL
browser_memory_monitor-0.0.3.dist-info/entry_points.txt
browser_memory_monitor-0.0.3.dist-info/top_level.txt
browser_memory_monitor-0.0.3.dist-info/RECORD
